ziva/__init__.py
ziva/chart_data.py
ziva/comm_package.py
ziva/compare_files.py
ziva/const.py
ziva/crc.py
ziva/data_compensation.py
ziva/exceptions.py
ziva/jda_to_dtv.py
ziva/mock.py
ziva/raw_converter.py
ziva/serialib.py
ziva/sm_monitor.py
ziva/ziva.py
ziva-0.2.7.dist-info/METADATA
ziva-0.2.7.dist-info/WHEEL
ziva-0.2.7.dist-info/top_level.txt
ziva-0.2.7.dist-info/RECORD
