Metadata-Version: 2.1
Name: ziva
Version: 0.2.7
Summary: Library for communicating with DMS-ziva based devices
Home-page: https://github.com/belingarb/ziva
Author: Bozidar Belingar
Author-email: bozidar.belingar@gmail.com
License: MIT
Platform: UNKNOWN
Classifier: License :: OSI Approved :: MIT License
Classifier: Programming Language :: Python
Classifier: Programming Language :: Python :: 3.7
Classifier: Programming Language :: Python :: Implementation :: CPython
Classifier: Programming Language :: Python :: Implementation :: PyPy
Requires-Python: >=3.7.0
Requires-Dist: pyserial (==3.5)
Requires-Dist: pandas (==1.3.5)
